django_leaf-2.1.2.dist-info/DESCRIPTION.rst
django_leaf-2.1.2.dist-info/METADATA
django_leaf-2.1.2.dist-info/metadata.json
django_leaf-2.1.2.dist-info/RECORD
django_leaf-2.1.2.dist-info/top_level.txt
django_leaf-2.1.2.dist-info/WHEEL
leaf/__init__.py
leaf/admin.py
leaf/apps.py
leaf/forms.py
leaf/helpers.py
leaf/models.py
leaf/page.py
leaf/urls.py
leaf/views.py
leaf/migrations/0001_initial.py
leaf/migrations/0001_initial.pyc
leaf/migrations/0002_add_page_node.py
leaf/migrations/0002_add_page_node.pyc
leaf/migrations/__init__.py
leaf/migrations/__init__.pyc
leaf/migrations/__pycache__/0001_initial.cpython-34.pyc
leaf/migrations/__pycache__/0002_add_page_node.cpython-34.pyc
leaf/migrations/__pycache__/__init__.cpython-34.pyc
leaf/static/leaf/css/admin.css
